{
  "ka": 1089,
  "an": 696,
  "sé": 505,
  "on": 486,
  "té": 457,
  "yo": 441,
  "pou": 411,
  "nou": 389,
  "pa": 368,
  "ki": 316,
  "mwen": 261,
  "ou": 255,
  "sa": 237,
  "fè": 228,
  "la": 178,
  "ni": 166,
  "di": 155,
  "kon": 147,
  "ké": 143,
  "si": 140,
  "adan": 140,
  "lè": 128,
  "moun": 126,
  "tout": 123,
  "kou": 123,
  "pé": 122,
  "a-y": 122,
  "mé": 102,
  "zòt": 101,
  "menm": 101,
  "vwè": 97,
  "viktò": 95,
  "pran": 90,
  "jan": 87,
  "pè": 82,
  "tini": 80,
  "ti": 76,
  "dé": 72,
  "san": 72,
  "épi": 72,
  "rivé": 66,
  "ja": 63,
  "èvè": 61,
  "pyè": 59,
  "ba": 57,
  "anba": 56,
  "fanm": 56,
  "palé": 55,
  "men": 55,
  "asi": 54,
  "travayè": 53,
  "fò": 53,
  "byen": 52,
  "ay": 50,
  "tètè": 50,
  "mété": 47,
  "biten": 47,
  "bèl": 47,
  "tan": 46,
  "jou": 45,
  "tèt": 45,
  "bon": 45,
  "konsa": 45,
  "anlè": 45,
  "nonm": 44,
  "pli": 43,
  "travay": 42,
  "vlé": 42,
  "pasé": 41,
  "ankò": 41,
  "kréyòl": 41,
  "gadé": 39,
  "rété": 38,
  "dòt": 38,
  "douvan": 38,
  "tou": 37,
  "dlo": 36,
  "pas": 35,
  "vini": 34,
  "gran": 33,
  "yé": 33,
  "ban": 33,
  "mò": 33,
  "sav": 33,
  "zyé": 32,
  "dèyè": 32,
  "koté": 32,
  "lang": 32,
  "yonn": 31,
  "kaz": 31,
  "vin": 31,
  "a-yo": 30,
  "toujou": 30,
  "lévé": 30,
  "mi": 30,
  "annou": 30,
  "sòti": 30,
  "tann": 30,
  "touvé": 29,
  "misyé": 29,
  "osi": 28,
  "apré": 28,
  "sèvi": 27,
  "dyab": 27,
  "kanmarad": 26,
  "manjé": 26,
  "an-mwen": 26,
  "bay": 26,
  "pi": 26,
  "konprann": 26,
  "rantré": 26,
  "fi-la": 26,
  "mandé": 25,
  "nèg": 25,
  "pawòl": 25,
  "non": 25,
  "hélé": 25,
  "alé": 25,
  "an-nou": 24,
  "lavi": 24,
  "kò": 24,
  "tousa": 24,
  "kwè": 24,
  "fèt": 23,
  "timoun": 23,
  "pati": 23,
  "noutout": 23,
  "wouvè": 22,
  "li": 22,
  "manman": 21,
  "gwadloup": 21,
  "avan": 21,
  "kè": 21,
  "oben": 21,
  "blan": 21,
  "maché": 21,
  "alò": 21,
  "larichès": 21,
  "sonjé": 20,
  "viv": 20,
  "pyé": 20,
  "ri": 20,
  "chèché": 20,
  "kouri": 20,
  "onlo": 20,
  "lékòl": 20,
  "man": 20,
  "a-w": 19,
  "bat": 19,
  "sizé": 19,
  "ouvriyé": 19,
  "jilyen": 19,
  "kapitalis": 19,
  "rann-nou": 19,
  "po": 18,
  "lapenn": 18,
  "tè": 18,
  "davwa": 18,
  "jis": 18,
  "lajan": 18,
  "chak": 18,
  "réponn": 18,
  "chanté": 18,
  "ayen": 18,
  "bout": 17,
  "onsèl": 17,
  "anmwé": 17,
  "las": 17,
  "dépi": 17,
  "plen": 17,
  "détwa": 17,
  "vyé": 17,
  "fanmi": 17,
  "kaz-la": 17,
  "dwèt": 17,
  "dapré": 17,
  "jen": 17,
  "timo": 17,
  "banmkouwi": 17,
  "péyi": 16,
  "lézòt": 16,
  "chivé": 16,
  "ola": 16,
  "kijan": 16,
  "vré": 16,
  "lé": 16,
  "padavwa": 16,
  "solid": 16,
  "bandé": 16,
  "bwa": 15,
  "mèt": 15,
  "do": 15,
  "mizè": 15,
  "vann": 15,
  "maré": 15,
  "kouté": 15,
  "lapen": 15,
  "doubout": 15,
  "mayé": 15,
  "fèmé": 15,
  "enmé": 15,
  "tibwen": 15,
  "alè": 15,
  "viré": 14,
  "koulé": 14,
  "bouch": 14,
  "wayayay": 14,
  "ès": 14,
  "konnèt": 14,
  "pòté": 14,
  "madanm": 14,
  "kout": 14,
  "fòs": 14,
  "santi": 14,
  "alòs": 14,
  "lanné": 14,
  "wi": 14,
  "kontinyé": 14,
  "somanbil": 14,
  "mésyé": 14,
  "prèmyé": 14,
  "mové": 13,
  "trapé": 13,
  "pozé": 13,
  "solèy": 13,
  "plis": 13,
  "fizi": 13,
  "jenn": 13,
  "maléré": 13,
  "lòt": 13,
  "ba-w": 13,
  "pwan": 13,
  "jaden": 13,
  "kriyé": 13,
  "mo": 13,
  "ba-y": 13,
  "krab": 13,
  "dèmen": 13,
  "ponmoun": 13,
  "voyé": 13,
  "sendikalis": 13,
  "travayè-la": 13,
  "kapitalis-la": 13,
  "pété": 12,
  "doulè": 12,
  "chimen": 12,
  "rivyè": 12,
  "maké": 12,
  "lannuit": 12,
  "gwo": 12,
  "monté": 12,
  "goumé": 12,
  "achté": 12,
  "fon": 12,
  "pannan": 12,
  "mal": 12,
  "rèd": 12,
  "moun-la": 12,
  "pri": 12,
  "fini": 12,
  "lantou": 12,
  "dèpi": 12,
  "ta": 12,
  "zen": 12,
  "zafè": 12,
  "tanbou": 12,
  "senn-la": 12,
  "dakò": 12,
  "sé-w": 12,
  "akoulélé": 12,
  "matété": 12,
  "lakou": 11,
  "menné": 11,
  "désann": 11,
  "tonbé": 11,
  "pon": 11,
  "anrajé": 11,
  "pèd": 11,
  "figi": 11,
  "jòdijou": 11,
  "bwè": 11,
  "chapé": 11,
  "lèwvwè": 11,
  "ziyanm": 11,
  "touléjou": 11,
  "vwa": 11,
  "en": 11,
  "kwi-la": 11,
  "di-nou": 11,
  "ba-yo": 11,
  "mami": 11,
  "paré": 10,
  "fè-nou": 10,
  "sèl": 10,
  "pléré": 10,
  "sèvèl": 10,
  "péyi-la": 10,
  "owa": 10,
  "vant": 10,
  "madanm-la": 10,
  "andidan": 10,
  "lanmè": 10,
  "pòkò": 10,
  "plas": 10,
  "tèks-la": 10,
  "woulé": 10,
  "aprésa": 10,
  "mannyòk": 10,
  "enpé": 10,
  "fè-y": 10,
  "ansanm": 10,
  "kontan": 10,
  "jòdila": 10,
  "sanm": 10,
  "lasa": 10,
  "somanbil-la": 10,
  "woy": 10,
  "sèk": 9,
  "atè": 9,
  "wòch": 9,
  "konpè": 9,
  "apiyé": 9,
  "évè": 9,
  "sab": 9,
  "kalité": 9,
  "toutmoun": 9,
  "kwi": 9,
  "chanjé": 9,
  "touné": 9,
  "lésé": 9,
  "koulè": 9,
  "zanba": 9,
  "mété-y": 9,
  "vansé": 9,
  "atann": 9,
  "fin": 9,
  "chyen": 9,
  "twa": 9,
  "pitit": 9,
  "lanmè-la": 9,
  "fwa": 9,
  "boug": 9,
  "fò-nou": 9,
  "avè": 9,
  "kay": 9,
  "kité": 9,
  "komansé": 9,
  "tiré": 9,
  "lalwa": 9,
  "sendika-la": 9,
  "fransé": 9,
  "savann": 8,
  "lanmò": 8,
  "sonné": 8,
  "vi": 8,
  "chayé": 8,
  "pit": 8,
  "latè": 8,
  "vou": 8,
  "lwen": 8,
  "van": 8,
  "ma": 8,
  "pòt": 8,
  "klè": 8,
  "tras": 8,
  "sanblé": 8,
  "jété": 8,
  "aprann": 8,
  "pèp": 8,
  "plant": 8,
  "alantou": 8,
  "louwa": 8,
  "bèf": 8,
  "bonjou": 8,
  "kouché": 8,
  "yenki": 8,
  "péchè-la": 8,
  "di-y": 8,
  "touvé-y": 8,
  "syèl": 8,
  "enki": 8,
  "pousa": 8,
  "déviré": 8,
  "lèspri": 8,
  "poutan": 8,
  "janmé": 8,
  "kimoun": 8,
  "bonmaten-la": 8,
  "poukisa": 8,
  "défann": 8,
  "kotésit": 8,
  "désidé": 8,
  "soukou": 8,
  "labitid": 8,
  "mò-la": 8,
  "chanbè": 8,
  "gèl": 7,
  "lafen": 7,
  "ban-nou": 7,
  "mitan": 7,
  "sou": 7,
  "poul": 7,
  "pann": 7,
  "toupatou": 7,
  "kont": 7,
  "mòn": 7,
  "sové": 7,
  "péyé": 7,
  "pyès": 7,
  "pétèt": 7,
  "mannyè": 7,
  "kèsyon": 7,
  "lontan": 7,
  "pyébwa": 7,
  "di-mwen": 7,
  "fi": 7,
  "dènyé": 7,
  "jwenn": 7,
  "parapòt": 7,
  "opozé": 7,
  "lidé": 7,
  "piti": 7,
  "misyé-la": 7,
  "awa": 7,
  "sitèlman": 7,
  "zen-la": 7,
  "jé": 7,
  "koupé": 7,
  "kilès": 7,
  "mèsi": 7,
  "dimanch": 7,
  "lak": 7,
  "téyat": 7,
  "oblijé": 7,
  "vo": 7,
  "pakèt": 7,
  "ékri": 7,
  "zanmi": 7,
  "bitasyon": 7,
  "senn": 7,
  "près": 7,
  "oswè-la": 7,
  "kenbé": 7,
  "mépri": 7,
  "zépòl": 7,
  "sendika": 7,
  "larichesse": 7,
  "sè": 7,
  "branch": 6,
  "wouj": 6,
  "zò": 6,
  "blo": 6,
  "fann": 6,
  "difé": 6,
  "mak": 6,
  "ouvè": 6,
  "lari": 6,
  "fouyé": 6,
  "wouklé": 6,
  "montré": 6,
  "gangné": 6,
  "fwèt": 6,
  "mélé": 6,
  "two": 6,
  "mès": 6,
  "zèb": 6,
  "hou": 6,
  "flè": 6,
  "mòso": 6,
  "bizwen": 6,
  "dòmi": 6,
  "anmitan": 6,
  "ban-mwen": 6,
  "nenpòt": 6,
  "anni": 6,
  "sans": 6,
  "pwason": 6,
  "toubòlman": 6,
  "lenj": 6,
  "déwò": 6,
  "manman-mwen": 6,
  "suiv": 6,
  "yotout": 6,
  "ant": 6,
  "klas": 6,
  "fwansé": 6,
  "estatistik": 6,
  "konpwann": 6,
  "sété": 6,
  "hak": 6,
  "jérè": 6,
  "sya": 6,
  "plato": 6,
  "toupannan": 6,
  "pòpòt-la": 6,
  "istwa": 6,
  "dè": 6,
  "biten-la": 6,
  "fout": 6,
  "konsidiré": 6,
  "konfyans": 6,
  "fanmi-la": 6,
  "pou-y": 6,
  "akou": 6,
  "lélé": 6,
  "bal": 6,
  "gason": 6,
  "adlin": 6,
  "sid-lanmérik": 6,
  "cholo": 6,
  "bouko": 6,
  "mwa": 5,
  "payé": 5,
  "sann": 5,
  "valé": 5,
  "cho": 5,
  "kokozyé": 5,
  "lèstonmak": 5,
  "konté": 5,
  "zanfan": 5,
  "sonmèy": 5,
  "lanmen": 5,
  "fouré": 5,
  "kòlè": 5,
  "kaskòd": 5,
  "lapwent": 5,
  "fès": 5,
  "aka": 5,
  "soulajé": 5,
  "kwen": 5,
  "obliyé": 5,
  "fèy": 5,
  "kyè": 5,
  "chaj": 5,
  "ondòt": 5,
  "magré": 5,
  "lilèt": 5,
  "plizyè": 5,
  "antan": 5,
  "nèg-la": 5,
  "sèten": 5,
  "asé": 5,
  "pousé": 5,
  "fen": 5,
  "bésé": 5,
  "jouwé": 5,
  "swé": 5,
  "séré": 5,
  "wòb": 5,
  "gwoka": 5,
  "répondè": 5,
  "èspéré": 5,
  "de": 5,
  "bwabwa": 5,
  "tousèl": 5,
  "malérèz-la": 5,
  "mari": 5,
  "timoun-la": 5,
  "lò": 5,
  "kouvè": 5,
  "avyon": 5,
  "fou": 5,
  "ho": 5,
  "manzè": 5,
  "tèlman": 5,
  "liv": 5,
  "baton": 5,
  "épi-y": 5,
  "frit": 5,
  "konsyans": 5,
  "farin": 5,
  "kyouyé": 5,
  "séla": 5,
  "bitasyon-la": 5,
  "rido-la": 5,
  "chanson": 5,
  "révé": 5,
  "plato-la": 5,
  "isidan": 5,
  "diskité": 5,
  "aprann-nou": 5,
  "tribinal": 5,
  "toutmoun-la": 5,
  "moman": 5,
  "lèsplikasyon": 5,
  "politik": 5,
  "wont": 5,
  "twòp": 5,
  "onkounan": 5,
  "latousen": 5,
  "nich": 5,
  "dansé": 5,
  "di-w": 5,
  "enben": 5,
  "sòstèn": 5,
  "klarans": 5,
  "lajistis": 5,
  "òbò": 5,
  "pèchè": 5,
  "dègné": 5,
  "swèf": 5,
  "féran": 5,
  "dèrèpo": 5,
  "ladévenn": 5,
  "volé": 4,
  "bal-a-fizi": 4,
  "dalo": 4,
  "laplas": 4,
  "popo": 4,
  "bòsko": 4,
  "arèsté": 4,
  "niyaj": 4,
  "swasantsèt": 4,
  "zorèy": 4,
  "bobo": 4,
  "simé": 4,
  "bò": 4,
  "lèv": 4,
  "koumansé": 4,
  "nankaz": 4,
  "tan-lasa": 4,
  "lavil": 4,
  "kochon": 4,
  "chajé": 4,
  "gra": 4,
  "mannèv": 4,
  "kòm": 4,
  "koko": 4,
  "lanm": 4,
  "toufé": 4,
  "mofwazé": 4,
  "pòch": 4,
  "gannyé": 4,
  "twèl": 4,
  "boutik": 4,
  "parèt": 4,
  "halé": 4,
  "soufè": 4,
  "milat": 4,
  "délè": 4,
  "kléré": 4,
  "chaben": 4,
  "rèv": 4,
  "dabòpouyonn": 4,
  "lèsklavaj": 4,
  "tè-la": 4,
  "jaden-la": 4,
  "zouti": 4,
  "planté": 4,
  "fwi": 4,
  "légim": 4,
  "déotwa": 4,
  "fò-mwen": 4,
  "pèsonn": 4,
  "men-la": 4,
  "tchenbé": 4,
  "plenn": 4,
  "akaz": 4,
  "zo": 4,
  "bondyé": 4,
  "lagwadloup": 4,
  "bannann": 4,
  "pannansitan": 4,
  "valè": 4,
  "manman-yo": 4,
  "pal": 4,
  "sèvi-mwen": 4,
  "atèla": 4,
  "twazyèm": 4,
  "bwa-la": 4,
  "planch": 4,
  "toupiti": 4,
  "konsidéré": 4,
  "nan": 4,
  "anpil": 4,
  "liv-la": 4,
  "tras-la": 4,
  "ek": 4,
  "tibren": 4,
  "siwvwè": 4,
  "maten": 4,
  "fil": 4,
  "apa": 4,
  "rupaire": 4,
  "ren": 4,
  "trèt": 4,
  "kabann": 4,
  "isi": 4,
  "gé": 4,
  "rakonté": 4,
  "bann": 4,
  "ranmasé": 4,
  "gaz": 4,
  "tablo-la": 4,
  "tris": 4,
  "trankil": 4,
  "abiyé": 4,
  "travay-la": 4,
  "kozé": 4,
  "rézon": 4,
  "dwètèt": 4,
  "pouri": 4,
  "mafi": 4,
  "réglé": 4,
  "biten-lasa": 4,
  "lang-la": 4,
  "nwè": 4,
  "pis": 4,
  "tin": 4,
  "noumenm": 4,
  "trasé": 4,
  "véyé": 4,
  "fouté": 4,
  "pisimé": 4,
  "titak": 4,
  "onjan": 4,
  "èvè-y": 4,
  "lagé": 4,
  "mizik": 4,
  "sousé": 4,
  "kondisyon": 4,
  "fizi-la": 4,
  "kannòt": 4,
  "tifi-la": 4,
  "ti-jan": 4,
  "lanmérik": 4,
  "blan-la": 4,
  "grap-a-kongo": 4,
  "sérémoni-la": 4,
  "lafet": 4,
  "albè": 4,
  "féfé": 4,
  "alen": 4,
  "tata": 4,
  "fré": 4,
  "gadévwè": 4,
  "ha": 4,
  "lavwa": 4,
  "kréyòl-gwadloup": 4,
  "woupwan": 4,
  "kalé": 4,
  "mòwnalyen": 4,
  "boukan": 3,
  "kraché": 3,
  "wèt": 3,
  "pòz": 3,
  "kyansé": 3,
  "chikayé": 3,
  "jik": 3,
  "manglo": 3,
  "konmen": 3,
  "négriyon": 3,
  "flangé": 3,
  "kayé": 3,
  "rat": 3,
  "souf": 3,
  "chouboulé": 3,
  "lèd": 3,
  "kontré": 3,
  "fréchè": 3,
  "nòz": 3,
  "dékoud": 3,
  "souri": 3,
  "penn": 3,
  "touf": 3,
  "mango": 3,
  "lokans": 3,
  "bannélo": 3,
  "lib": 3,
  "sal": 3,
  "bonda": 3,
  "lòt-la": 3,
  "haché": 3,
  "gri": 3,
  "jouné": 3,
  "toulongalé": 3,
  "nanm": 3,
  "zòdi": 3,
  "kalbas": 3,
  "didiko": 3,
  "bityé": 3,
  "naté": 3,
  "pilo": 3,
  "débarasé": 3,
  "tayé": 3,
  "afòs": 3,
  "bokantaj": 3,
  "baré": 3,
  "rann": 3,
  "débaké": 3,
  "chalviré": 3,
  "kouli": 3,
  "twota": 3,
  "divini": 3,
  "blé": 3,
  "grenné": 3,
  "rèstan": 3,
  "baké": 3,
  "ofè": 3,
  "enkyèt": 3,
  "zansèt": 3,
  "piplis": 3,
  "patat": 3,
  "pwa": 3,
  "souvan": 3,
  "silvyàn": 3,
  "wòl": 3,
  "kuizin-la": 3,
  "vè": 3,
  "anplis": 3,
  "kann": 3,
  "ma-la": 3,
  "kalkilé": 3,
  "mwayen": 3,
  "gouyé": 3,
  "poupou": 3,
  "lanmwatyé": 3,
  "atè-la": 3,
  "kòd": 3,
  "balan": 3,
  "bo": 3,
  "tanté": 3,
  "japé": 3,
  "siren": 3,
  "tòl": 3,
  "boula": 3,
  "makè": 3,
  "way": 3,
  "syèl-la": 3,
  "magrésa": 3,
  "lapli": 3,
  "konmansé": 3,
  "èspliké": 3,
  "senk": 3,
  "lésé-y": 3,
  "moun-lasa": 3,
  "manman-la": 3,
  "lanbi": 3,
  "wonm": 3,
  "mandé-y": 3,
  "viré-monté": 3,
  "tala": 3,
  "vwè-y": 3,
  "wouplonjé": 3,
  "jounou": 3,
  "bra": 3,
  "dézyèm-la": 3,
  "grandè": 3,
  "féyaj": 3,
  "bennyé": 3,
  "onpakèt": 3,
  "lanmòd": 3,
  "ladésizyon": 3,
  "sila": 3,
  "toulématen": 3,
  "foto": 3,
  "foto-la": 3,
  "wè": 3,
  "yomenm": 3,
  "laj": 3,
  "woupati": 3,
  "savé": 3,
  "janmen": 3,
  "touvé-mwen": 3,
  "ponyonn": 3,
  "palé-w": 3,
  "fet": 3,
  "kréyol": 3,
  "moun-an": 3,
  "asiré": 3,
  "likibè": 3,
  "dévlopé": 3,
  "diféran": 3,
  "kréyé": 3,
  "démounaj": 3,
  "lajòl": 3,
  "sosyété": 3,
  "biwo": 3,
  "sanmdi": 3,
  "midi": 3,
  "chonjé": 3,
  "trenné": 3,
  "gwadloupéyen": 3,
  "konnyé": 3,
  "pito": 3,
  "mouton": 3,
  "rédé": 3,
  "limyè": 3,
  "dézòd": 3,
  "pwòp": 3,
  "lonji": 3,
  "répété": 3,
  "dis": 3,
  "graté": 3,
  "mwenmenm": 3,
  "kagou": 3,
  "jwé": 3,
  "jounal": 3,
  "kolé": 3,
  "tousuit": 3,
  "kongné": 3,
  "kaché": 3,
  "antré": 3,
  "bonswa": 3,
  "lòd": 3,
  "méyè": 3,
  "égri": 3,
  "zòrèy": 3,
  "kouraj": 3,
  "mété-yo": 3,
  "poko": 3,
  "fè-mwen": 3,
  "anvi": 3,
  "santé": 3,
  "kèchòz": 3,
  "chèf": 3,
  "simétan": 3,
  "lézòm": 3,
  "konprann-li": 3,
  "grandi": 3,
  "foukan": 3,
  "anpéché-yo": 3,
  "politisyen": 3,
  "lwa": 3,
  "jistis": 3,
  "kifè": 3,
  "dékouvè": 3,
  "montré-yo": 3,
  "fason": 3,
  "kouzyé": 3,
  "pòtékò": 3,
  "konsi": 3,
  "diskou": 3,
  "mo-la": 3,
  "tonnè": 3,
  "lachas": 3,
  "mizè-la": 3,
  "dépité": 3,
  "kanmarad-la": 3,
  "dan": 3,
  "élèksyon": 3,
  "menné-nou": 3,
  "di-yo": 3,
  "katchimen": 3,
  "mandé-zòt": 3,
  "menné-y": 3,
  "frè": 3,
  "papa": 3,
  "pridòm": 3,
  "pibyen": 3,
  "kou-lasa": 3,
  "ogalo": 3,
  "va": 3,
  "woté": 3,
  "krévé": 3,
  "monchè": 3,
  "oti": 3,
  "grèv": 3,
  "pousuiv": 3,
  "lak-la": 3,
  "gita": 3,
  "kouté-yo": 3,
  "pòtré": 3,
  "rédé-yo": 3,
  "chanm": 3,
  "voukoum": 3,
  "dérifizé": 3,
  "apwann": 3,
  "wélélé": 3,
  "massembo": 3,
  "fété": 3,
  "omwen": 3,
  "kivédi": 3,
  "boutèy": 3,
  "sakré": 3,
  "trinté": 3,
  "kidonk": 3,
  "sèvis": 3,
  "jéra": 3,
  "bèf-la": 3,
  "sitwouy": 3,
  "poy": 3,
  "kolèt": 3,
  "jojo": 3,
  "menmjan": 3,
  "zélèv": 3,
  "sentwòz": 3,
  "woulo": 3,
  "kadans": 3,
  "lérépondè": 3,
  "tanboudibrèz": 3,
  "vou-menm": 3,
  "ko": 3,
  "cham": 3,
  "dlo-la": 3,
  "janbé": 3,
  "chaché": 3,
  "bari": 3,
  "chapo": 3,
  "rèna": 3,
  "kan": 3,
  "lenbé": 3,
  "lévwazinaj": 3,
  "bandé-bandé": 3,
  "doukou": 2,
  "fran": 2,
  "manman-zanfan": 2,
  "ravin": 2,
  "makout": 2,
  "floup": 2,
  "gonmbo": 2,
  "kapwé": 2,
  "gobé": 2,
  "dépant": 2,
  "péyi-pé-bouch": 2,
  "pousyè": 2,
  "foufou": 2,
  "lanké": 2,
  "sak": 2,
  "pach": 2,
  "képi": 2,
  "koukyanm": 2,
  "ti-zing": 2,
  "zobèl": 2,
  "mwèl": 2,
  "chivi": 2,
  "chwa": 2,
  "tif": 2,
  "wa-ya-yay": 2,
  "nèstò": 2,
  "fap-fap": 2,
  "dézyèm": 2,
  "bim-bo-po": 2,
  "pincemail": 2,
  "may": 2,
  "monbrino": 2,
  "mouch": 2,
  "kòchté": 2,
  "tarèt": 2,
  "aladébandad": 2,
  "kwa": 2,
  "monté-désann": 2,
  "mémwa": 2,
  "ankavé": 2,
  "lètch": 2,
  "dékont": 2,
  "kadav": 2,
  "blès": 2,
  "chimen-chyen": 2,
  "woufizé": 2,
  "lèspwa": 2,
  "krankran": 2,
  "liminé": 2,
  "fwè-gogo": 2,
  "takatak": 2,
  "mwa-d-mé-lasa": 2,
  "jwen": 2,
  "vakans": 2,
  "lank": 2,
  "avòté": 2,
  "tòch": 2,
  "nennenn": 2,
  "dada": 2,
  "sésé": 2,
  "kip": 2,
  "manfou": 2,
  "soudé": 2,
  "kéloyid": 2,
  "rizèt": 2,
  "sivoké": 2,
  "sèlman": 2,
  "poèm-lasa": 2,
  "rétif": 2,
  "lésé-mwen": 2,
  "chans": 2,
  "boyo": 2,
  "réisi": 2,
  "hazyé": 2,
  "négyon": 2,
  "tap": 2,
  "laliwondaj": 2,
  "dousiné": 2,
  "zévan": 2,
  "anmenmditan": 2,
  "lyanné": 2,
  "kwazé": 2,
  "kannal": 2,
  "ranpli": 2,
  "vid": 2,
  "piman": 2,
  "épé": 2,
  "vyann": 2,
  "vayan": 2,
  "péchè": 2,
  "lité": 2,
  "koud": 2,
  "daré": 2,
  "kabrit": 2,
  "malpwòpté": 2,
  "balyé": 2,
  "movèzté": 2,
  "lonbraj": 2,
  "mansousyé": 2,
  "woumété": 2,
  "dématé": 2,
  "chabon": 2,
  "nétwayé": 2,
  "won": 2,
  "banbou": 2,
  "déchaj": 2,
  "danmjann": 2,
  "angoudi": 2,
  "bayè": 2,
  "zésant": 2,
  "swanyé": 2,
  "zégrè": 2,
  "siyon": 2,
  "fenfon": 2,
  "gou": 2,
  "chenn": 2,
  "angajé": 2,
  "béké": 2,
  "gonflé": 2,
  "blan-péyi": 2,
  "ranjé": 2,
  "malè": 2,
  "zendyen": 2,
  "bonnè": 2,
  "dantèl": 2,
  "lolo": 2,
  "bouden": 2,
  "siriyen": 2,
  "séparé": 2,
  "prété": 2,
  "négrès": 2,
  "nèf": 2,
  "malpalan": 2,
  "rapòté": 2,
  "majò": 2,
  "ganmé": 2,
  "ras": 2,
  "wousi": 2,
  "zéklari": 2,
  "kako": 2,
  "bouklé": 2,
  "gangann": 2,
  "tanven": 2,
  "zèsklav": 2,
  "ègzisté": 2,
  "pèl": 2,
  "malanga": 2,
  "pòyò": 2,
  "papay": 2,
  "rasin": 2,
  "rarman": 2,
  "pwodui": 2,
  "otila": 2,
  "tèks": 2,
  "telchid": 2,
  "kawo": 2,
  "plant-lasa": 2,
  "anplas": 2,
  "kontèl": 2,
  "gawni": 2,
  "toultan": 2,
  "antiyè": 2,
  "lajouné": 2,
  "gwosè": 2,
  "anlè-y": 2,
  "kouman": 2,
  "talè": 2,
  "pap": 2,
  "pyé-la": 2,
  "domèstik": 2,
  "rivé-w": 2,
  "chofé": 2,
  "bouwo": 2,
  "lizyè": 2,
  "fifin": 2,
  "planni": 2,
  "zannimo": 2,
  "pran-yo": 2,
  "fal": 2,
  "ravèt": 2,
  "krikèt": 2,
  "lavòl": 2,
  "klendenden": 2,
  "limé": 2,
  "razyé": 2,
  "anbafèy": 2,
  "anfon": 2,
  "gawoulé": 2,
  "gwovant": 2,
  "févriyé": 2,
  "tizi": 2,
  "solèy-la": 2,
  "séryé": 2,
  "chaklè": 2,
  "labé": 2,
  "kèksyon": 2,
  "ankijan": 2,
  "tipawòl-lasa": 2,
  "avè-y": 2,
  "fè-w": 2,
  "grenn": 2,
  "lapèch": 2,
  "lapyè": 2,
  "péché": 2,
  "lansbètran": 2,
  "soulyé": 2,
  "kuit": 2,
  "chaléré": 2,
  "plonjé": 2,
  "woukomansé": 2,
  "priyédyé": 2,
  "bonkyè": 2,
  "vèw": 2,
  "vé": 2,
  "rann-mwen": 2,
  "wouyé": 2,
  "pran-y": 2,
  "boug-la": 2,
  "mè": 2,
  "kriyé-y": 2,
  "awjan": 2,
  "vivasyon": 2,
  "konstrui": 2,
  "manjé-la": 2,
  "kal": 2,
  "lavé": 2,
  "golèt": 2,
  "chè": 2,
  "alèkilé": 2,
  "danjé": 2,
  "vwayaj": 2,
  "lafwa": 2,
  "petit": 2,
  "plita": 2,
  "losyon": 2,
  "bwèt": 2,
  "léjè": 2,
  "mandé-mwen": 2,
  "lanvòl": 2,
  "paj": 2,
  "koton": 2,
  "fawdé": 2,
  "lanmwa": 2,
  "tanzantan": 2,
  "poudavwa": 2,
  "limenm": 2,
  "koulè-la": 2,
  "débòdé": 2,
  "lanmou": 2,
  "lanvi": 2,
  "yen": 2,
  "mas": 2,
  "matématik": 2,
  "fo": 2,
  "konésans": 2,
  "premié": 2,
  "fasil": 2,
  "matjé": 2,
  "poutji": 2,
  "enmen": 2,
  "pòpòt": 2,
  "alèz": 2,
  "le": 2,
  "konstaté": 2,
  "listwa": 2,
  "klé": 2,
  "kilti": 2,
  "rèmounaj": 2,
  "nouvo": 2,
  "dominasyon": 2,
  "pèyi": 2,
  "pen": 2,
  "kouran": 2,
  "woukonnèt": 2,
  "soni": 2,
  "vèt": 2,
  "agrikòl": 2,
  "janm": 2,
  "chiré": 2,
  "rido": 2,
  "manti-mantè": 2,
  "chanson-la": 2,
  "sò": 2,
  "tèbè": 2,
  "pézé": 2,
  "blagé": 2,
  "fòl": 2,
  "lilèt-lasa": 2,
  "labatwa": 2,
  "débat": 2,
  "disparèt": 2,
  "bétiz": 2,
  "tab-la": 2,
  "pita": 2,
  "tabouré": 2,
  "tren": 2,
  "pòt-la": 2,
  "jouné-la": 2,
  "avèti": 2,
  "pizyè": 2,
  "pran-fè": 2,
  "fè-yo": 2,
  "rakonté-nou": 2,
  "karann-senk": 2,
  "rizé": 2,
  "bitasyon-lasa": 2,
  "dézèspéré": 2,
  "kyiiiip": 2,
  "dèyè-y": 2,
  "désiré": 2,
  "gè": 2,
  "santi-mwen": 2,
  "lidé-lasa": 2,
  "papyé": 2,
  "tribinal-la": 2,
  "razè": 2,
  "manch": 2,
  "jilé": 2,
  "lajan-la": 2,
  "sou-lasa": 2,
  "lépiti": 2,
  "krazé": 2,
  "mil": 2,
  "zam": 2,
  "vitman": 2,
  "achté-yo": 2,
  "fwans": 2,
  "dwa": 2,
  "latranblad": 2,
  "toutotan": 2,
  "favè": 2,
  "mangné": 2,
  "présé": 2,
  "réfléchi": 2,
  "sitiyasyon-la": 2,
  "arété": 2,
  "fwa-la": 2,
  "lè-la": 2,
  "prévwa": 2,
  "gouvèlman": 2,
  "engra": 2,
  "machè": 2,
  "grigné": 2,
  "lou": 2,
  "di-vou": 2,
  "kouté-mwen": 2,
  "enté": 2,
  "entélèktyèl": 2,
  "konsèy": 2,
  "sou-la": 2,
  "lékòl-la": 2,
  "kamarad": 2,
  "konprann-nou": 2,
  "zatrap": 2,
  "bouché": 2,
  "tranglé-nou": 2,
  "boukèt": 2,
  "pikèt": 2,
  "konférans": 2,
  "vòlè": 2,
  "lotorizasyon": 2,
  "né": 2,
  "bobi": 2,
  "yè": 2,
  "misyé-lasa": 2,
  "hon": 2,
  "vwè-zòt": 2,
  "tisè": 2,
  "fyèl": 2,
  "manman-vè": 2,
  "talèla": 2,
  "lésé-nou": 2,
  "plon": 2,
  "fouté-y": 2,
  "woupran": 2,
  "nonmé": 2,
  "bastè": 2,
  "wèèè": 2,
  "anmenmdètan": 2,
  "anbala": 2,
  "rèsté": 2,
  "sendikalis-la": 2,
  "mouchwa": 2,
  "wouvè-y": 2,
  "gadé-yo": 2,
  "patron-la": 2,
  "rèsponsabilité": 2,
  "difikilté": 2,
  "ékonomi": 2,
  "pré": 2,
  "onpil": 2,
  "manti": 2,
  "olyé": 2,
  "kochi": 2,
  "souflé-zòt": 2,
  "sèn": 2,
  "gratèdkòd-la": 2,
  "gratèdpapyé-la": 2,
  "chopin": 2,
  "dimi-po": 2,
  "gratèdjouné-la": 2,
  "jimo": 2,
  "lavéyé": 2,
  "pépa": 2,
  "koulé-yo": 2,
  "téyat-la": 2,
  "lòdè": 2,
  "malgraté": 2,
  "sèvi-nou": 2,
  "bouwo-la": 2,
  "nouchak": 2,
  "drapo": 2,
  "toumoun": 2,
  "janti": 2,
  "èché": 2,
  "pò": 2,
  "kat": 2,
  "kouch": 2,
  "tab": 2,
  "woyoyoy": 2,
  "manman-nou": 2,
  "fanm-chatengn": 2,
  "poto-mitan": 2,
  "mannyé": 2,
  "bèlté": 2,
  "granjou": 2,
  "dirèksyon": 2,
  "kèlanswa": 2,
  "kofré": 2,
  "limanité": 2,
  "atoutfòs": 2,
  "ta-yo": 2,
  "solda": 2,
  "sèvi-yo": 2,
  "pwazon": 2,
  "andwa": 2,
  "akwèdi": 2,
  "lad": 2,
  "lédikasyon": 2,
  "asosyasyon": 2,
  "a-zòt": 2,
  "moun-blan": 2,
  "réponn-yo": 2,
  "légalité": 2,
  "véridik-véritab": 2,
  "marie-france": 2,
  "f-l": 2,
  "damba": 2,
  "sèptanm": 2,
  "novanm": 2,
  "obò": 2,
  "préparé": 2,
  "wonm-la": 2,
  "èsprimé": 2,
  "sipòté": 2,
  "chalanndé": 2,
  "anman": 2,
  "sé-y": 2,
  "dézòdyè": 2,
  "pouvwa": 2,
  "soukwé": 2,
  "aséfyé": 2,
  "fésé": 2,
  "lalit": 2,
  "larézon": 2,
  "sianka": 2,
  "lafet-la": 2,
  "mantjé": 2,
  "lizin": 2,
  "filibè": 2,
  "sétout": 2,
  "han": 2,
  "pasé-w": 2,
  "chimen-la": 2,
  "konmisyon": 2,
  "bèl-la": 2,
  "éwo": 2,
  "potoko": 2,
  "atanaz": 2,
  "konfiti": 2,
  "gèy": 2,
  "bouyi-y": 2,
  "toula": 2,
  "malad": 2,
  "danyèl": 2,
  "istwa-la": 2,
  "sèlmanti": 2,
  "dépawfwa": 2,
  "vitrin": 2,
  "kanta": 2,
  "pon-la": 2,
  "kwédé": 2,
  "lyannaj": 2,
  "ki-w": 2,
  "òpsyon": 2,
  "kolèj": 2,
  "sonny": 2,
  "lanméri": 2,
  "byendéfwa": 2,
  "douvanjou": 2,
  "kontribann": 2,
  "pyès-fanm": 2,
  "mouchwè": 2,
  "anpizé": 2,
  "sanglé": 2,
  "fanm-bitasyon": 2,
  "kolyé": 2,
  "zanno": 2,
  "voumtak": 2,
  "taktak": 2,
  "lang-lafwans": 2,
  "akizé-la": 2,
  "awtik": 2,
  "lafwans": 2,
  "réjyonnal-la": 2,
  "lanviwonnaj": 2,
  "lavi-la": 2,
  "labou": 2,
  "senten": 2,
  "sòs": 2,
  "laplaj": 2,
  "bokit": 2,
  "swè": 2,
  "pòk": 2,
  "fosé": 2,
  "tèré": 2,
  "pougalé": 2,
  "kèpi": 2,
  "rouj": 2,
  "banmkoukwi": 2,
  "kawòs": 2,
  "nonm-la": 2,
  "cham-la": 2,
  "kanno-la": 2,
  "ranmé": 2,
  "néyé": 2,
  "pay": 2,
  "chouval": 2,
  "dézè-la": 2,
  "prens-la": 2,
  "kèkontan": 2,
  "titin": 2,
  "ladyablès": 2,
  "pat": 2,
  "mizi": 2,
  "routyé": 2,
  "kann-la": 2,
  "fouté-mwen": 2,
  "bawòt": 2,
  "anbenn": 2,
  "témwen": 2,
  "wap": 2,
  "soufwans": 2,
  "ravyoli": 2,
  "ooo": 2,
  "anbwa": 2,
  "pyé-flanbwayan": 1,
  "téré-séré": 1,
  "plen-vant": 1,
  "bwèy": 1,
  "lantèn": 1,
  "zanfan-lékòl": 1,
  "tan-nou": 1,
  "fiksé": 1,
  "pèdi": 1,
  "anvlimé": 1,
  "marlo": 1,
  "pichin": 1,
  "fòlman": 1,
  "kwout": 1,
  "palaviré": 1,
  "hokèt": 1,
  "tòtyé": 1,
  "viré-mwen": 1,
  "anpawtaj": 1,
  "bougo": 1,
  "opozé-mwen": 1,
  "réisé": 1,
  "fòsé-nou": 1,
  "téré": 1,
  "hélé-toufé": 1,
  "lansan": 1,
  "òksidé": 1,
  "chajman": 1,
  "pougalé-mwen": 1,
  "foré": 1,
  "détòtyé": 1,
  "pit-a-kòk": 1,
  "kouvé": 1,
  "zé": 1,
  "maské": 1,
  "bréché": 1,
  "zòtèy": 1,
  "ni-pyé": 1,
  "poulèt": 1,
  "zenga": 1,
  "lojé": 1,
  "sizé-o-swè": 1,
  "kawbé": 1,
  "dénous": 1,
  "vòl": 1,
  "plivyé": 1,
  "kikiwit": 1,
  "mokodjonbi": 1,
  "twalèt": 1,
  "banza": 1,
  "poké": 1,
  "pyès-kann": 1,
  "dous": 1,
  "zotolan": 1,
  "lodè": 1,
  "monben": 1,
  "hazyé-péyi": 1,
  "sully": 1,
  "claire": 1,
  "bébian": 1,
  "lélanné": 1,
  "monbruno": 1,
  "zamia": 1,
  "koté-lasa": 1,
  "fonksyonné": 1,
  "yomenmyomenm": 1,
  "détou": 1,
  "lakolonizasyon": 1,
  "tikrapo": 1,
  "golomin": 1,
  "fobou": 1,
  "pyé-fouyapen": 1,
  "zémondis": 1,
  "lonbrik": 1,
  "dèmi": 1,
  "toutouni": 1,
  "gwopyé": 1,
  "douslèt": 1,
  "kilibibi": 1,
  "sik-a-pistach": 1,
  "bonbon-mousach": 1,
  "topinanbou": 1,
  "vwazin": 1,
  "tigout": 1,
  "man-jak": 1,
  "babyé": 1,
  "jipon": 1,
  "kuis": 1,
  "kri": 1,
  "kalimèt": 1,
  "lwenzanlwen": 1,
  "koupèd-kann": 1,
  "mapou": 1,
  "wòch-fè": 1,
  "dokè": 1,
  "mason": 1,
  "mènuizyé": 1,
  "venndouz": 1,
  "métyé": 1,
  "lanmizè": 1,
  "véyé-yo": 1,
  "louwé-yo": 1,
  "bòn": 1,
  "gwokyap": 1,
  "mawché": 1,
  "mori": 1,
  "salé": 1,
  "farin-mannyòk": 1,
  "barik": 1,
  "fondòk": 1,
  "sanganné": 1,
  "chaspann": 1,
  "gòjé": 1,
  "salézon": 1,
  "katoutou": 1,
  "zékal": 1,
  "latannyé": 1,
  "bakwa": 1,
  "granbwa": 1,
  "balé-dou": 1,
  "santyé": 1,
  "masakré": 1,
  "féray": 1,
  "rans": 1,
  "kanpèch": 1,
  "chari": 1,
  "moyé": 1,
  "kabwèt": 1,
  "fondè": 1,
  "foyé": 1,
  "zanma": 1,
  "gòlèt": 1,
  "kabèt": 1,
  "salopté": 1,
  "débri": 1,
  "lyann": 1,
  "galba": 1,
  "trésé": 1,
  "sigin": 1,
  "pannyé": 1,
  "pliché": 1,
  "tij": 1,
  "pripri": 1,
  "nas": 1,
  "anbistan": 1,
  "lanbouchi": 1,
  "anbalaj": 1,
  "pans": 1,
  "fèblan": 1,
  "résipyan": 1,
  "glèz": 1,
  "chodyè": 1,
  "potich": 1,
  "koukyan": 1,
  "branbrann": 1,
  "konblaj": 1,
  "wouplanté": 1,
  "gaya": 1,
  "koubari": 1,
  "gayak": 1,
  "balata": 1,
  "florès": 1,
  "mèrizyé": 1,
  "pwaryé": 1,
  "pwazonné": 1,
  "sézon": 1,
  "lawouzé": 1,
  "konvwa": 1,
  "plantasyon": 1,
  "fwitaj": 1,
  "fimyé": 1,
  "patiraj": 1,
  "sèklé": 1,
  "bòkaz": 1,
  "rakouri": 1,
  "plan": 1,
  "mangròv": 1,
  "kochonni": 1,
  "sispann": 1,
  "zéfé": 1,
  "izé": 1,
  "dèyèjou": 1,
  "dégajé": 1,
  "mangrov": 1,
  "lizaj": 1,
  "rijton": 1,
  "ponnyi": 1,
  "kolon": 1,
  "fòwtin": 1,
  "kokannyé": 1,
  "èspwaté": 1,
  "fvè": 1,
  "anvarifyé": 1,
  "domenn": 1,
  "anfrich": 1,
  "pévi": 1,
  "dékatyé": 1,
  "lòtbò": 1,
  "blan-griyav": 1,
  "pèsé": 1,
  "aristokat": 1,
  "abizan": 1,
  "boulvèsé": 1,
  "salè": 1,
  "alinyé": 1,
  "kontra": 1,
  "déchiré": 1,
  "vètèlè": 1,
  "vèpèlè": 1,
  "masalè": 1,
  "divali": 1,
  "oblivé": 1,
  "vandouvan": 1,
  "prétanta": 1,
  "malaba": 1,
  "kalkita": 1,
  "malmenné": 1,
  "kòlpòté": 1,
  "bagaj": 1,
  "malèt": 1,
  "anflé": 1,
  "myélé": 1,
  "malfouti": 1,
  "bwaskò": 1,
  "aprésyé": 1,
  "konplé": 1,
  "sousoun": 1,
  "klérant": 1,
  "miziré": 1,
  "rapyannè": 1,
  "bagoulè": 1,
  "libanè": 1,
  "véyè": 1,
  "grangrèk": 1,
  "konmès": 1,
  "mélanjé": 1,
  "kren": 1,
  "santinèl": 1,
  "konploté": 1,
  "fòsé": 1,
  "lonnè": 1,
  "rènyé": 1,
  "dèsten": 1,
  "bagyolè": 1,
  "bata": 1,
  "grandizè": 1,
  "dékanté": 1,
  "solbòkò": 1,
  "griyé": 1,
  "plotonné": 1,
  "dékatman": 1,
  "plasé": 1,
  "chodri": 1,
  "blésé": 1,
  "sisèptib": 1,
  "réplikè": 1,
  "kalazaza": 1,
  "takté": 1,
  "bouskilé": 1,
  "rèspé": 1,
  "blenm": 1,
  "frizé": 1,
  "bato": 1,
  "kòsté": 1,
  "jodijou": 1,
  "étwèt": 1,
  "krenn": 1,
  "ansoufwans": 1,
  "lèkti": 1,
  "répons": 1,
  "antouré": 1,
  "jaden-lasa": 1,
  "brilé": 1,
  "travay-li": 1,
  "kitan": 1,
  "lèsklèvaj": 1,
  "andéwò": 1,
  "kalté": 1,
  "plant-la": 1,
  "zépis": 1,
  "bazilik": 1,
  "sitwon": 1,
  "pèsil": 1,
  "ten": 1,
  "parèy": 1,
  "rimèd": 1,
  "simenn-kontra": 1,
  "té-péyi": 1,
  "swen": 1,
  "kajo": 1,
  "karo": 1,
  "léti": 1,
  "sèlri": 1,
  "siv": 1,
  "désèwten": 1,
  "pyé-sitron": 1,
  "ponch": 1,
  "géri": 1,
  "pyé-miskad-la": 1,
  "pyé-kowòsòl-la": 1,
  "désè": 1,
  "fléri": 1,
  "kawòt": 1,
  "navé": 1,
  "pyé-pòyò": 1,
  "rézilta": 1,
  "timtim": 1,
  "fèy-papyé": 1,
  "ligorin": 1,
  "èstati": 1,
  "lakòl": 1,
  "lagé-mwen": 1,
  "tèt-la": 1,
  "bouden-la": 1,
  "gòch": 1,
  "ponnyé": 1,
  "maré-y": 1,
  "tchouyé-y": 1,
  "tchouyé": 1,
  "savann-la": 1,
  "mété-w": 1,
  "mwen-la": 1,
  "mayé-mwen": 1,
  "konfès": 1,
  "démaré-mwen": 1,
  "démaré-w": 1,
  "onfwa": 1,
  "démaré": 1,
  "maré-mwen": 1,
  "vòltijé": 1,
  "branché": 1,
  "zandoli": 1,
  "sisizèb": 1,
  "bèkté": 1,
  "kèk": 1,
  "foumi-fòl": 1,
  "pyé-papay": 1,
  "genbo": 1,
  "fas": 1,
  "voras": 1,
  "mabouya": 1,
  "débouyé-y": 1,
  "gounouy": 1,
  "krapo": 1,
  "akò": 1,
  "marengwen": 1,
  "répi": 1,
  "siwanné": 1,
  "chinyé-la": 1,
  "klou": 1,
  "réyé": 1,
  "anpangal": 1,
  "manzèmari": 1,
  "séri": 1,
  "ibiskis": 1,
  "chifonné-yo": 1,
  "dérédi": 1,
  "trimé": 1,
  "louké": 1,
  "antòtyé": 1,
  "kabouya": 1,
  "evè": 1,
  "lalin": 1,
  "vanté": 1,
  "déjouké": 1,
  "texte": 1,
  "inédit": 1,
  "kakadò": 1,
  "roger": 1,
  "valy-plaisant": 1,
  "chéchrès": 1,
  "anchéchrès": 1,
  "yaya": 1,
  "filèt": 1,
  "limon": 1,
  "vèdigri": 1,
  "alanvè": 1,
  "aransò": 1,
  "mèg": 1,
  "nadan": 1,
  "pòyò-la": 1,
  "blip": 1,
  "vèglé": 1,
  "konmansman": 1,
  "livènaj": 1,
  "fréchi": 1,
  "wouziné": 1,
  "enkèt": 1,
  "anchouké": 1,
  "dékatiyaj": 1,
  "kèsyon-lasa": 1,
  "kenbwa": 1,
  "poukirézon": 1,
  "lègzanp": 1,
  "tèks-lasa": 1,
  "mantalité": 1,
  "chouké": 1,
  "malérèz": 1,
  "pyès-kaz": 1,
  "larèstan": 1,
  "diri": 1,
  "létwa": 1,
  "pwòpté": 1,
  "bòdlanmè": 1,
  "najé": 1,
  "bivèt": 1,
  "toupréla": 1,
  "anpenn": 1,
  "èché-y": 1,
  "batzyé": 1,
  "mayo": 1,
  "lakontantman": 1,
  "mi-y": 1,
  "lawjan": 1,
  "woumété-y": 1,
  "sala": 1,
  "zen-lasa": 1,
  "sennyè": 1,
  "bo-y": 1,
  "prémyé": 1,
  "dyaman": 1,
  "chouk": 1,
  "lakanpangn": 1,
  "admèt": 1,
  "kenn-kont": 1,
  "matéryo": 1,
  "potomitan": 1,
  "van-la": 1,
  "foyédifé-la": 1,
  "fèytòl": 1,
  "garenn": 1,
  "kalòj": 1,
  "rimèd-razyé": 1,
  "jolivyé": 1,
  "anmenmtan": 1,
  "klwazon-la": 1,
  "iskèlèt-la": 1,
  "oblijé-w": 1,
  "chawpantyé": 1,
  "planch-la": 1,
  "blendé": 1,
  "pèwmèt": 1,
  "ganm": 1,
  "pwotéjé": 1,
  "kuizin": 1,
  "danjé-lasa": 1,
  "inèd-tan": 1,
  "sèkèy": 1,
  "flo": 1,
  "fwomajé": 1,
  "kwafé-yo": 1,
  "fòm": 1,
  "kaka-kabrit": 1,
  "nat": 1,
  "chinyon": 1,
  "aktè": 1,
  "banndésiné": 1,
  "ansanm-ansanm": 1,
  "enfirmyèz-la": 1,
  "openpan": 1,
  "kwafé": 1,
  "dwòl-jan": 1,
  "ofè-y": 1,
  "cartier": 1,
  "krèm": 1,
  "douch": 1,
  "fifiné-y": 1,
  "anbenn-anbenn": 1,
  "lòdè-la": 1,
  "chanm-la": 1,
  "annui": 1,
  "tizanfan": 1,
  "nouyòk": 1,
  "pantagoni": 1,
  "vyètnam": 1,
  "èstèbèkwè": 1,
  "aprédavwa": 1,
  "konmsidiré": 1,
  "mond": 1,
  "kòwbo-la": 1,
  "réyisi": 1,
  "kwafè-yo": 1,
  "dèt": 1,
  "zoréyé-la": 1,
  "fouwé": 1,
  "wouj-a-lèv": 1,
  "dimi-bann": 1,
  "tib": 1,
  "métal": 1,
  "woupran-y": 1,
  "dépozé-y": 1,
  "ofon-ofon": 1,
  "asèlfen": 1,
  "konnyéla": 1,
  "mounmò": 1,
  "dwòlté-la": 1,
  "komik": 1,
  "mens": 1,
  "lonbrik-la": 1,
  "ahak": 1,
  "lòpilans": 1,
  "tranblé": 1,
  "opozé-y": 1,
  "lòwvwè": 1,
  "damou": 1,
  "budapest": 1,
  "bucarest": 1,
  "paris": 1,
  "charlottesville": 1,
  "vil-lasa": 1,
  "parèt-mwen": 1,
  "donan": 1,
  "pwokiré-mwen": 1,
  "lèspérans": 1,
  "brital-la": 1,
  "vil-alasa": 1,
  "vil-la": 1,
  "lawvwè": 1,
  "kapab": 1,
  "ann": 1,
  "woupran-mwen": 1,
  "malovant": 1,
  "janvyé": 1,
  "larantré": 1,
  "koul": 1,
  "roch": 1,
  "lez": 1,
  "èvè-w": 1,
  "wobè": 1,
  "bak": 1,
  "siwo-la": 1,
  "bay-alé": 1,
  "gid-la": 1,
  "fomasion": 1,
  "lang-yo": 1,
  "lasians": 1,
  "pliziè": 1,
  "manniè": 1,
  "tretman": 1,
  "léplisouvan": 1,
  "déziem": 1,
  "red": 1,
  "larel": 1,
  "agoch": 1,
  "lin": 1,
  "andidanbway-la": 1,
  "anlo": 1,
  "asepté": 1,
  "fok": 1,
  "pwobablité": 1,
  "étidié": 1,
  "chif": 1,
  "lamenm": 1,
  "bien": 1,
  "larépons": 1,
  "pétet": 1,
  "mwens": 1,
  "gerec-f": 1,
  "endé": 1,
  "anchay": 1,
  "rafayel": 1,
  "konfian": 1,
  "koreksion": 1,
  "sej": 1,
  "restog": 1,
  "korijé": 1,
  "fot": 1,
  "lonk": 1,
  "fwansoi": 1,
  "konsey": 1,
  "liliane": 1,
  "yann": 1,
  "maman": 1,
  "hayot": 1,
  "kréyol-la": 1,
  "mawonaj": 1,
  "syanséka": 1,
  "èspèktak": 1,
  "notion": 1,
  "race": 1,
  "humaine": 1,
  "moral": 1,
  "gobineau": 1,
  "anthénor": 1,
  "firmin": 1,
  "osinon": 1,
  "éléman": 1,
  "édikatè": 1,
  "istaj": 1,
  "école": 1,
  "normale": 1,
  "formateur": 1,
  "illetrisme": 1,
  "lumière": 1,
  "enseignement": 1,
  "gérard": 1,
  "lauriette": 1,
  "pofondè": 1,
  "lukubérisme": 1,
  "filozofi": 1,
  "prensip": 1,
  "itil": 1,
  "endispansab": 1,
  "méné": 1,
  "kalpat": 1,
  "konpòwtèman": 1,
  "bien-être": 1,
  "est": 1,
  "extérieur": 1,
  "érè": 1,
  "kontwolé": 1,
  "séjò": 1,
  "lalyénasyon": 1,
  "konsékans": 1,
  "réyalité": 1,
  "vérité": 1,
  "kalkil": 1,
  "ispiritiyalité": 1,
  "envité": 1,
  "pwoblèm": 1,
  "solisyon": 1,
  "libèté": 1,
  "konpòtasyon": 1,
  "téritwa": 1,
  "lapyétòn": 1,
  "vil": 1,
  "sentàn": 1,
  "boulva": 1,
  "ibéné": 1,
  "anka": 1,
  "woukonnèt-ou": 1,
  "dodo": 1,
  "zòfi": 1,
  "vwèyé": 1,
  "fwan": 1,
  "twazilé": 1,
  "grantans": 1,
  "dè-è-fò": 1,
  "kannon": 1,
  "té-é": 1,
  "son-on": 1,
  "zangi": 1,
  "taté": 1,
  "nanan": 1,
  "soupson": 1,
  "ovan": 1,
  "pèyi-la": 1,
  "andéwò-la": 1,
  "mouvman": 1,
  "sèché": 1,
  "plaj": 1,
  "gaoulé": 1,
  "kraké": 1,
  "plat-pyé": 1,
  "saèl": 1,
  "dous-la": 1,
  "tanponné": 1,
  "tranglé-maté": 1,
  "sosolé-dématé": 1,
  "parad": 1,
  "edisyon": 1,
  "parabole": 1,
  "démokatpawòl": 1,
  "pyès-lasa": 1,
  "kabanné": 1,
  "déba": 1,
  "fòskouch": 1,
  "fòt": 1,
  "langaj": 1,
  "tribiché": 1,
  "vomyétan": 1,
  "chèchè": 1,
  "jouè": 1,
  "zanmi-frè": 1,
  "plantè": 1,
  "mètlékòl": 1,
  "prèmye": 1,
  "nwèsè": 1,
  "koulis-la": 1,
  "laposésyon": 1,
  "plat-a-men": 1,
  "ting-ting": 1,
  "gratkwwi": 1,
  "gounouf": 1,
  "pantalon": 1,
  "pyèsté": 1,
  "tousé": 1,
  "triko": 1,
  "divinè": 1,
  "nonpli": 1,
  "mati": 1,
  "blèblè": 1,
  "glas": 1,
  "dépozé": 1,
  "tipòpòt": 1,
  "gratèd-kòd": 1,
  "sòt": 1,
  "chantè": 1,
  "dézòd-la": 1,
  "sonnkès": 1,
  "avèg": 1,
  "touris": 1,
  "rézonné": 1,
  "tipoul": 1,
  "chinyé": 1,
  "ka-w": 1,
  "foumi": 1,
  "rara": 1,
  "tòktòk": 1,
  "sòlèy": 1,
  "oswè": 1,
  "toudi": 1,
  "kenbwazè": 1,
  "mannitizè": 1,
  "mofwazè": 1,
  "séparasyon-la": 1,
  "lanp": 1,
  "pyès-la": 1,
  "tablo": 1,
  "tounéviré": 1,
  "chèz": 1,
  "sèn-la": 1,
  "timoun-lasa": 1,
  "enposib": 1,
  "jistan": 1,
  "léswa": 1,
  "pozisyon": 1,
  "milyé": 1,
  "tann-li": 1,
  "wouvini": 1,
  "balé-la": 1,
  "siren-la": 1,
  "tousenp": 1,
  "pliyé": 1,
  "byenmèsi": 1,
  "démon-lasa": 1,
  "òò": 1,
  "kouté-nou": 1,
  "asiz": 1,
  "chèz-la": 1,
  "atann-vou": 1,
  "kasé": 1,
  "fré-la": 1,
  "koko-la": 1,
  "jéré": 1,
  "pwonmèt-mwen": 1,
  "pòv": 1,
  "kèktan": 1,
  "grenn-moutad": 1,
  "pasé-nou": 1,
  "plizanpli": 1,
  "pwopriyétè": 1,
  "fonsyé": 1,
  "bigidi": 1,
  "bous": 1,
  "machin": 1,
  "bèt": 1,
  "pwèl": 1,
  "pannyé-la": 1,
  "pwofitan-la": 1,
  "èksplwatè": 1,
  "langré": 1,
  "péyé-nou": 1,
  "ayen-ditou": 1,
  "lacharité": 1,
  "klas-la": 1,
  "ouviyé": 1,
  "aplis": 1,
  "lapòt-la": 1,
  "konnèt-li": 1,
  "mésyézédam": 1,
  "mètlékòl-la": 1,
  "gras": 1,
  "konnèt-vou": 1,
  "palé-mwen": 1,
  "vèwmin-lasa": 1,
  "toutan": 1,
  "rèspétan": 1,
  "manké": 1,
  "bo-mwen": 1,
  "kotési": 1,
  "fou-mwen": 1,
  "konplosité": 1,
  "tann-la": 1,
  "biyé-palapenn": 1,
  "ranvwayé-mwen": 1,
  "poubon": 1,
  "fòs-la": 1,
  "gyab": 1,
  "ésa": 1,
  "japrouv": 1,
  "résité": 1,
  "kité-yo": 1,
  "toulézòt": 1,
  "nòt": 1,
  "trétri": 1,
  "dayèpouyonn": 1,
  "avoka": 1,
  "kafityè": 1,
  "tèt-a-lak": 1,
  "sansi-la": 1,
  "patri": 1,
  "touplen": 1,
  "granboutik": 1,
  "tab-lasa": 1,
  "biyé": 1,
  "alakous": 1,
  "létè": 1,
  "soren": 1,
  "fouti": 1,
  "propriyétè-fonsyé": 1,
  "granboutik-la": 1,
  "béké-la": 1,
  "aligné": 1,
  "révolisyon": 1,
  "swasann-sèt": 1,
  "bastè-la": 1,
  "jandàm": 1,
  "lawmé": 1,
  "magazen-soulyé": 1,
  "jous": 1,
  "pouriti": 1,
  "sendika-lasa": 1,
  "fonksyònè": 1,
  "gouvèné": 1,
  "gouvèlman-la": 1,
  "lawmé-la": 1,
  "milyon-la": 1,
  "volé-nou": 1,
  "lwa-la": 1,
  "toukonprann": 1,
  "grad": 1,
  "bòné": 1,
  "ojis": 1,
  "èksplwaté": 1,
  "omodihèp": 1,
  "fèlè": 1,
  "réyalizé": 1,
  "pokosyon-lasa": 1,
  "koudach": 1,
  "branka": 1,
  "signé": 1,
  "bren-chivé": 1,
  "fanmi-pré": 1,
  "gran-fanmi": 1,
  "pran-mwen": 1,
  "déjà": 1,
  "èspliké-yo": 1,
  "yochak": 1,
  "dézabiyé": 1,
  "senk-é-kat": 1,
  "bonnuit": 1,
  "dèmen-spéra-dyé": 1,
  "sén": 1,
  "mòl": 1,
  "konjé": 1,
  "réglo": 1,
  "toulémwa": 1,
  "fouyapòt": 1,
  "vwè-nou": 1,
  "néta": 1,
  "pasé-mwen": 1,
  "toumanté-mwen": 1,
  "atètipo": 1,
  "janmdoubwa": 1,
  "dépann": 1,
  "dwòl": 1,
  "woooy": 1,
  "antann-nou": 1,
  "mètdékòl": 1,
  "granklas": 1,
  "kad": 1,
  "masko": 1,
  "entélijan": 1,
  "wèèèè": 1,
  "sant": 1,
  "konnèt-nou": 1,
  "pwofité": 1,
  "avansé-nou": 1,
  "mèt-lékòl": 1,
  "lézòt-la": 1,
  "aristokrat": 1,
  "mwa-la": 1,
  "timonné": 1,
  "kenn": 1,
  "lapozisyon": 1,
  "ploton": 1,
  "chap": 1,
  "enpo": 1,
  "jou-lasa": 1,
  "timtim-bwasèk": 1,
  "kouyonné-nou": 1,
  "mòdé": 1,
  "mèt-lékòl-la": 1,
  "rédé-nou": 1,
  "jan-lasa": 1,
  "kyolé": 1,
  "maléré-la": 1,
  "ensisitè": 1,
  "fonksyonnè": 1,
  "pongnèt": 1,
  "woutouvé": 1,
  "élèksyon-lasa": 1,
  "féré-nou": 1,
  "sennatè": 1,
  "jénéral": 1,
  "manm": 1,
  "initil": 1,
  "parazit": 1,
  "kouyonné": 1,
  "blagè": 1,
  "sizo": 1,
  "kwafè": 1,
  "oblanchi": 1,
  "bilten": 1,
  "bwèt-a-lin": 1,
  "vòt": 1,
  "pikèt-la": 1,
  "kòd-la": 1,
  "rakousi": 1,
  "défwa": 1,
  "akilè": 1,
  "osèryé": 1,
  "vwè-mwen": 1,
  "radyo": 1,
  "sinéma": 1,
  "télévizyon": 1,
  "kòn": 1,
  "pwopagann": 1,
  "lavérité": 1,
  "jérova": 1,
  "avantis": 1,
  "pòs": 1,
  "vis": 1,
  "poulbwa": 1,
  "gwoupman": 1,
  "entérè": 1,
  "aprann-yo": 1,
  "madrag": 1,
  "pawòl-la": 1,
  "lonji-nou": 1,
  "bas": 1,
  "bwaré": 1,
  "toulédé": 1,
  "zòttout": 1,
  "dézagréman": 1,
  "swèf-li": 1,
  "touné-viré": 1,
  "kourandè": 1,
  "santiman-la": 1,
  "istwa-lasa": 1,
  "malboug": 1,
  "gyòb": 1,
  "kon-w": 1,
  "tòchon": 1,
  "fè-an": 1,
  "monnami": 1,
  "touché-w": 1,
  "woutouné": 1,
  "kenbé-w": 1,
  "frisi": 1,
  "chiré-nou": 1,
  "tout-sòt-kalité": 1,
  "anmennaj": 1,
  "anfiyansé": 1,
  "onkyolé": 1,
  "madè": 1,
  "kòché": 1,
  "nanbwa": 1,
  "diférans-lasa": 1,
  "langaj-la": 1,
  "menmparèy": 1,
  "fè-la": 1,
  "koré": 1,
  "lèlmi-la": 1,
  "ponnyèt": 1,
  "onmèd": 1,
  "lèlmi": 1,
  "kenbé-nou": 1,
  "soutini-nou": 1,
  "rédé-y": 1,
  "piké-mwen": 1,
  "ranvoyé": 1,
  "kaka": 1,
  "frenné": 1,
  "dirèk": 1,
  "ankèt": 1,
  "vrai": 1,
  "kasmanntèt": 1,
  "loto": 1,
  "noua": 1,
  "dan-y": 1,
  "fò-zòt": 1,
  "kazak": 1,
  "baré-nou": 1,
  "bizwen-nou": 1,
  "rapòté-y": 1,
  "lèmal": 1,
  "japlòd": 1,
  "kyoulé": 1,
  "pèp-la": 1,
  "oblijé-yo": 1,
  "lagé-yo": 1,
  "képi-wouj": 1,
  "fòsé-y": 1,
  "wouba": 1,
  "anpéché": 1,
  "mako": 1,
  "dérèspèté-nou": 1,
  "simé-kouyé": 1,
  "pòté-pèt": 1,
  "lachyas": 1,
  "oblijé-y": 1,
  "tach-la": 1,
  "pran-nou": 1,
  "gwosi": 1,
  "jakèt": 1,
  "konba-la": 1,
  "ploton-la": 1,
  "alyansé-nou": 1,
  "on-òt": 1,
  "onlawmé": 1,
  "kon-y": 1,
  "chatouyé-y": 1,
  "dwèt-la": 1,
  "kyòk": 1,
  "lansanm": 1,
  "pwen": 1,
  "zòtchak": 1,
  "pan": 1,
  "toupré": 1,
  "pyès-pòyò": 1,
  "vini-zòt": 1,
  "réinyon-la": 1,
  "aboutsouf": 1,
  "zonbi": 1,
  "soukwé-y": 1,
  "pasé-y": 1,
  "fou-y": 1,
  "révòlvè": 1,
  "hen": 1,
  "drésé-y": 1,
  "finchyé": 1,
  "linèt": 1,
  "aa": 1,
  "konfèdmanti": 1,
  "sèvi-y": 1,
  "konpangn": 1,
  "vyéfanm": 1,
  "mésyé-lasa": 1,
  "sizé-zòt": 1,
  "fotèy": 1,
  "dépliyé-y": 1,
  "téléfonné-nou": 1,
  "oswa": 1,
  "mandé-nou": 1,
  "pwenté": 1,
  "pichon": 1,
  "nuit": 1,
  "classe": 1,
  "ouvrière": 1,
  "mél": 1,
  "kriyé-zòt": 1,
  "rèsponsabilité-lasa": 1,
  "konprann-zòt": 1,
  "réinyon": 1,
  "wousouvwè": 1,
  "plent": 1,
  "kotizasyon-la": 1,
  "cash": 1,
  "lémwa": 1,
  "pansé": 1,
  "difisil": 1,
  "boug-fou": 1,
  "pofité": 1,
  "distribiyé": 1,
  "trak": 1,
  "manifèstasyon": 1,
  "rèprézantatif": 1,
  "santral": 1,
  "frans": 1,
  "lagòch": 1,
  "épousa": 1,
  "négosiyasyon": 1,
  "okouran": 1,
  "lanné-lasa": 1,
  "délégasyon": 1,
  "fò-yo": 1,
  "amélyorasyon": 1,
  "ouvriyé-la": 1,
  "long": 1,
  "plim": 1,
  "délégé": 1,
  "kité-zòt": 1,
  "montré-mwen": 1,
  "kité-mwen": 1,
  "kyouyé-y": 1,
  "bat-dèyè": 1,
  "rakonté-mwen": 1,
  "bouré": 1,
  "soulé-nou": 1,
  "èvèv": 1,
  "ovantatè": 1,
  "défann-nou": 1,
  "bondaté": 1,
  "anvlòp": 1,
  "achté-zòt": 1,
  "padèyè": 1,
  "joué": 1,
  "toumbélé": 1,
  "yé-yé": 1,
  "san-la": 1,
  "limiyon-la": 1,
  "étenn": 1,
  "milè": 1,
  "vizyè": 1,
  "kochon-planch": 1,
  "pichonné": 1,
  "nwèsè-la": 1,
  "dèwò": 1,
  "gratèdtè-la": 1,
  "jouké": 1,
  "pak-la": 1,
  "machin-la": 1,
  "konsonmé": 1,
  "hat-la": 1,
  "piti-a-piti": 1,
  "diskou-la": 1,
  "mizik-la": 1,
  "siklòn": 1,
  "filao": 1,
  "vwè-yo": 1,
  "jouk-la": 1,
  "gratèdlannuit": 1,
  "tifé": 1,
  "tanbouyé": 1,
  "vyémadanm": 1,
  "andèy": 1,
  "akoté": 1,
  "senn-lasa": 1,
  "vyéfanl": 1,
  "vyéyès": 1,
  "gwoup": 1,
  "lit": 1,
  "lison": 1,
  "éséyé": 1,
  "rézoud": 1,
  "mèt-yo": 1,
  "konbat": 1,
  "èksplwatasyon": 1,
  "dévenn-la": 1,
  "kè-la": 1,
  "vòlè-la": 1,
  "koukyanm-la": 1,
  "frè-mwen": 1,
  "anbakou": 1,
  "koulwa": 1,
  "koulèv": 1,
  "jouk": 1,
  "mankré-pa": 1,
  "boutou": 1,
  "too": 1,
  "matòch": 1,
  "pikwa": 1,
  "ankourajé": 1,
  "anmizé-zòt": 1,
  "vit": 1,
  "apenn-apenn": 1,
  "zòtmenm": 1,
  "gratèdkòd": 1,
  "gratèdpapyé": 1,
  "penga": 1,
  "santi-zòt": 1,
  "kit": 1,
  "pyès-téyat": 1,
  "varé": 1,
  "jé-la": 1,
  "lign-la": 1,
  "vòltijé-yo": 1,
  "maji": 1,
  "lévé-zòt": 1,
  "anmè": 1,
  "raché": 1,
  "kouto-la": 1,
  "libéré": 1,
  "ajounou": 1,
  "vwèjou": 1,
  "ralé": 1,
  "dévlopé-y": 1,
  "kyé": 1,
  "fami": 1,
  "talon": 1,
  "pòtòkò": 1,
  "bòtzè": 1,
  "konpléto": 1,
  "gyè": 1,
  "lakaz": 1,
  "dékòl": 1,
  "wouméné": 1,
  "savan": 1,
  "gason-la": 1,
  "alafwa": 1,
  "monboug": 1,
  "figyi": 1,
  "nòstròm": 1,
  "simenn": 1,
  "annòd": 1,
  "pòw": 1,
  "manmzèl-la": 1,
  "telman": 1,
  "ovwa": 1,
  "mandé-yo": 1,
  "èché-yo": 1,
  "owsèvé": 1,
  "plaj-la": 1,
  "dékòl-la": 1,
  "jwenn-yo": 1,
  "mankyé": 1,
  "dra": 1,
  "wòz": 1,
  "jonn": 1,
  "ii": 1,
  "mèt-a-mannyòk": 1,
  "dani": 1,
  "jilyèt": 1,
  "vayan-konbatan": 1,
  "mètfédam": 1,
  "jèwti": 1,
  "lisèt": 1,
  "sévi": 1,
  "dinyité": 1,
  "morisèt": 1,
  "fanm-kanm": 1,
  "natali": 1,
  "bénéfis": 1,
  "pwennbik": 1,
  "ala": 1,
  "mariz": 1,
  "koutiryèz": 1,
  "doudou": 1,
  "dyèz": 1,
  "dyézé": 1,
  "simagré": 1,
  "bisiklèt": 1,
  "baskèt": 1,
  "kous": 1,
  "sotwèl": 1,
  "gazèl": 1,
  "marijo": 1,
  "rèldo": 1,
  "dansèz": 1,
  "chantèz": 1,
  "jaklin": 1,
  "aksidan": 1,
  "dòktè-fèy": 1,
  "lanati": 1,
  "rimèd-hazyé": 1,
  "sèkrétèz": 1,
  "biki": 1,
  "patwon": 1,
  "lantoupriz": 1,
  "chofè-kanmyon": 1,
  "mékannisyen": 1,
  "pipich": 1,
  "nonm-blan": 1,
  "déklaré": 1,
  "olagya": 1,
  "pawòl-lasa": 1,
  "péyi-lasa": 1,
  "tan-mwen": 1,
  "èspésyalman": 1,
  "plantasyon-la": 1,
  "tivil-la": 1,
  "granvil-la": 1,
  "propriyété": 1,
  "lajan-bénéfis": 1,
  "réponn-mwen": 1,
  "nò-lanmérik": 1,
  "sòlda": 1,
  "lagyè-lendépandans": 1,
  "rhodes": 1,
  "island": 1,
  "lagyè-sésésyon": 1,
  "kiba": 1,
  "es": 1,
  "modél": 1,
  "jénérozité": 1,
  "jodi-la": 1,
  "fanmasi": 1,
  "vè-dlo": 1,
  "pen-la": 1,
  "boulanjé": 1,
  "rèstoran": 1,
  "dépiwvwè": 1,
  "koté-yo": 1,
  "chanm-lotèl": 1,
  "kanmenmsi": 1,
  "fo-nou": 1,
  "pliplis": 1,
  "timoun-gason": 1,
  "abo": 1,
  "lonnè-é-rèspé": 1,
  "pyété": 1,
  "lapòt": 1,
  "jennjan": 1,
  "krétyen": 1,
  "bibliyotèk": 1,
  "swadizandi": 1,
  "popilasyon-moun": 1,
  "anréyalité": 1,
  "préché": 1,
  "lévanjil": 1,
  "prédikatè": 1,
  "sosyété-lasa": 1,
  "pèp-lasa": 1,
  "diférans": 1,
  "dwa-sivik": 1,
  "dwa-sosyal": 1,
  "misitikri-la": 1,
  "tòtòy-yo": 1,
  "légliz": 1,
  "eks": 1,
  "mété-nou": 1,
  "sikoté": 1,
  "èvè-nou": 1,
  "sid": 1,
  "chapékò": 1,
  "sivik": 1,
  "sosyal": 1,
  "simityè": 1,
  "kapèstè-bélo": 1,
  "kanpangn": 1,
  "kanmfò": 1,
  "lafanmi": 1,
  "òwganizé": 1,
  "sérémoni": 1,
  "vénéré": 1,
  "défen": 1,
  "jénèrasyon": 1,
  "rèmonté": 1,
  "péyòd": 1,
  "zasyèt": 1,
  "ozuil": 1,
  "tèrbolizé": 1,
  "névè": 1,
  "foul": 1,
  "dèyè-la": 1,
  "liyannaj": 1,
  "langue": 1,
  "et": 1,
  "culture": 1,
  "regionales": 1,
  "posésyon-la": 1,
  "wouviré": 1,
  "douvan-la": 1,
  "animé": 1,
  "chanté-la": 1,
  "zébisola": 1,
  "émalélé": 1,
  "vénérasyon": 1,
  "afriken": 1,
  "kikongo": 1,
  "travèsé": 1,
  "jénérasyon-la": 1,
  "ritmé": 1,
  "minui": 1,
  "bouké": 1,
  "flè-la": 1,
  "wouzé": 1,
  "libérasyon": 1,
  "woumenné-yo": 1,
  "padèyè-la": 1,
  "sakré-la": 1,
  "jénérasyon": 1,
  "rétrovizè": 1,
  "féba": 1,
  "moukté": 1,
  "gran-anman": 1,
  "fétay": 1,
  "sanfwa": 1,
  "pawòl-anmè": 1,
  "maloblijan": 1,
  "jiré": 1,
  "wonmyè": 1,
  "tifanm": 1,
  "paspò": 1,
  "vwayajé": 1,
  "dèkwa": 1,
  "fi-anmizi": 1,
  "maréchal": 1,
  "woulévé": 1,
  "kalpata": 1,
  "fanm-mayolèz": 1,
  "kòz": 1,
  "fanm-gyenm": 1,
  "tòd": 1,
  "détòd": 1,
  "toumantri": 1,
  "fanm-didiko": 1,
  "fanm-laplenn-lin": 1,
  "lasosyété": 1,
  "pwofitasyon": 1,
  "ponm-kannèl": 1,
  "rayisman": 1,
  "pawòl-senk-é-kat": 1,
  "pawòl-bigidi": 1,
  "konnet": 1,
  "chal": 1,
  "sonson": 1,
  "selman": 1,
  "simié": 1,
  "lafet-tala": 1,
  "vié": 1,
  "matrité": 1,
  "lanmes": 1,
  "bel": 1,
  "kanpann": 1,
  "non-tala": 1,
  "primié": 1,
  "kolonizasion": 1,
  "prèmié": 1,
  "lod": 1,
  "gouvènè": 1,
  "blénac": 1,
  "kabestè": 1,
  "rijwenn": 1,
  "foyal": 1,
  "atjelman": 1,
  "fodfwans": 1,
  "gwo-mòn": 1,
  "lonjé": 1,
  "lariviè": 1,
  "galion": 1,
  "dénel": 1,
  "pié": 1,
  "vè-pré": 1,
  "vréman": 1,
  "péplé": 1,
  "déblozon": 1,
  "sinistré": 1,
  "mòn-wouj": 1,
  "ajoupa-bouyon": 1,
  "baspwent": 1,
  "gouvènman": 1,
  "ripéplé": 1,
  "matnik": 1,
  "ritounen": 1,
  "volkan": 1,
  "pelé": 1,
  "pwopozé": 1,
  "konsésion": 1,
  "moman-taa": 1,
  "frékanté": 1,
  "sen-piè": 1,
  "maldo": 1,
  "gran-la": 1,
  "dènyé-la": 1,
  "manman-y": 1,
  "non-lasa": 1,
  "kras": 1,
  "papa-yo": 1,
  "ansent": 1,
  "ta-y": 1,
  "èspédyé-y": 1,
  "soté": 1,
  "sourit": 1,
  "maman-y": 1,
  "jòdi-la": 1,
  "rann-li": 1,
  "rifizé": 1,
  "swasanndizan": 1,
  "kanmenm": 1,
  "poukwa": 1,
  "boutik-la": 1,
  "ozabwa": 1,
  "chèché-y": 1,
  "atann-mwen": 1,
  "jèwton": 1,
  "kowosòl": 1,
  "kilo": 1,
  "rètouné": 1,
  "gaz-la": 1,
  "rèta": 1,
  "séléra": 1,
  "kouyonnad": 1,
  "trenné-w": 1,
  "pokosyon": 1,
  "séléra-la": 1,
  "chayé-w": 1,
  "vlé-mwen": 1,
  "bènwa": 1,
  "blaf": 1,
  "yépa": 1,
  "fabris": 1,
  "sara": 1,
  "avengers": 1,
  "taktak-la": 1,
  "konstans": 1,
  "sèt": 1,
  "primè": 1,
  "gato": 1,
  "agoulouganfal": 1,
  "paté": 1,
  "woché": 1,
  "sirèl": 1,
  "patisri": 1,
  "rawman": 1,
  "lasanblan": 1,
  "dapré-y": 1,
  "olasa": 1,
  "aaa": 1,
  "dézòdyèz": 1,
  "kilòt": 1,
  "entérésan": 1,
  "enmé-yo": 1,
  "édé-yo": 1,
  "enn": 1,
  "patisri-la": 1,
  "vwazinaj-la": 1,
  "chat": 1,
  "konpann": 1,
  "rakoun": 1,
  "klémans": 1,
  "touvé-yo": 1,
  "tann-vou": 1,
  "miklon": 1,
  "konkonm": 1,
  "jennfi-la": 1,
  "afwo-la": 1,
  "dè-y": 1,
  "ki-y": 1,
  "granpapa-y": 1,
  "granmanman-y": 1,
  "nègrès": 1,
  "badibou": 1,
  "akwè-y": 1,
  "douté-w": 1,
  "chivé-la": 1,
  "founi": 1,
  "arété-w": 1,
  "kwafèz": 1,
  "jèks": 1,
  "kòdé": 1,
  "lis": 1,
  "aprézan": 1,
  "otan": 1,
  "pèwmanant": 1,
  "konchonni-lasa": 1,
  "pennyé": 1,
  "tuto": 1,
  "entèwnèt": 1,
  "alapaj": 1,
  "koutzyé": 1,
  "ozékla": 1,
  "papi": 1,
  "féré": 1,
  "anmwééé": 1,
  "foto-lasa": 1,
  "mawdi": 1,
  "désanm": 1,
  "bébèl": 1,
  "lisé": 1,
  "ripaj": 1,
  "dékatman-lasa": 1,
  "lòpsyon": 1,
  "zélèv-la": 1,
  "jouné-lasa": 1,
  "lokèl": 1,
  "pèdsouf": 1,
  "nouvèl": 1,
  "èstébékwè": 1,
  "nouvélis-la": 1,
  "pwosé": 1,
  "asèpté": 1,
  "rézònman": 1,
  "matrisyèl": 1,
  "péripési": 1,
  "lang-lasa": 1,
  "nasyonnal": 1,
  "lègzanmen": 1,
  "konkou": 1,
  "sosyété-la": 1,
  "sètifika": 1,
  "capes": 1,
  "èspésyal": 1,
  "ansennyé": 1,
  "konkou-agrégasyon": 1,
  "akadémi": 1,
  "profésè": 1,
  "agréjé-kréyòl": 1,
  "sitiyasyon-lasa": 1,
  "défans": 1,
  "konstitisyon": 1,
  "patrimwàn": 1,
  "kongré-la": 1,
  "voté": 1,
  "modifikasyon": 1,
  "konstitisyon-la": 1,
  "minis-lajistis": 1,
  "garde": 1,
  "des": 1,
  "sceaux": 1,
  "sénatè-la": 1,
  "dépité-la": 1,
  "konsititisyon-la": 1,
  "larépiblik": 1,
  "sèvis-ladministrasyon": 1,
  "nòwmalité": 1,
  "sosyal-la": 1,
  "kantité": 1,
  "santiman": 1,
  "émosyònman": 1,
  "moun-èspésyal": 1,
  "tradui": 1,
  "alòkifè": 1,
  "annaks": 1,
  "pouki": 1,
  "maké-lasa": 1,
  "lèspwi": 1,
  "bokanté": 1,
  "méchansté": 1,
  "kalbandé": 1,
  "toutbiten": 1,
  "ayo": 1,
  "pani": 1,
  "fwansé-la": 1,
  "dialecte": 1,
  "voyé-y": 1,
  "kasav": 1,
  "rimé": 1,
  "zouk": 1,
  "chanté-y": 1,
  "natirèl": 1,
  "léko": 1,
  "ravin-la": 1,
  "dégouté": 1,
  "akontinyé": 1,
  "bougonné": 1,
  "koken": 1,
  "pwòspéré": 1,
  "volè": 1,
  "alèz-kon-blèz": 1,
  "falèz": 1,
  "wonchonné": 1,
  "bab": 1,
  "antòch": 1,
  "chigné": 1,
  "séké": 1,
  "lavalas": 1,
  "tòbòk": 1,
  "zékobèl": 1,
  "fyèl-é-kouraj": 1,
  "kimafoutiésa": 1,
  "péké": 1,
  "pépa-la": 1,
  "lanmè-kwazé": 1,
  "paka": 1,
  "wach": 1,
  "prangad": 1,
  "silan": 1,
  "bousyè": 1,
  "sonméy": 1,
  "palé-la": 1,
  "tè-gras": 1,
  "kolè": 1,
  "avoté": 1,
  "lasan": 1,
  "gwò": 1,
  "oksidé": 1,
  "kans": 1,
  "détòvè": 1,
  "bovo": 1,
  "flanboyan": 1,
  "aw": 1,
  "défran": 1,
  "tèré-séré": 1,
  "plen-van": 1,
  "brèy": 1,
  "ti-wèt": 1,
  "latènn": 1,
  "vol": 1,
  "gwomo": 1,
  "chuch": 1,
  "balonné": 1,
  "èk": 1,
  "poz": 1,
  "koutyanm": 1,
  "tchansé": 1,
  "lèstonbé": 1,
  "èlp": 1,
  "konnen": 1,
  "arèté": 1,
  "déziyèm": 1,
  "pétè": 1,
  "pédi": 1,
  "anvlmé": 1,
  "matlo": 1,
  "panchinn": 1,
  "folman": 1,
  "krout": 1,
  "fwè": 1,
  "boulvès": 1,
  "palavré": 1,
  "léd": 1,
  "hòkèt": 1,
  "totéyé": 1,
  "sèlèy": 1,
  "lasonjé": 1,
  "èskoté": 1,
  "pwoché": 1,
  "pwès": 1,
  "jènn": 1,
  "réjyon-la": 1,
  "jan-la": 1,
  "réfizé": 1,
  "èpi": 1,
  "goua": 1,
  "pwens": 1,
  "balkon": 1,
  "kawòs-la": 1,
  "prézanté": 1,
  "moso": 1,
  "galri": 1,
  "tak": 1,
  "souplé": 1,
  "tenba": 1,
  "asépté": 1,
  "fyanséz": 1,
  "opa": 1,
  "traversé": 1,
  "dètwoya": 1,
  "jès": 1,
  "wouvrin": 1,
  "klé-la": 1,
  "cham-m-la": 1,
  "mégrí": 1,
  "dyab-la": 1,
  "èskèlèt": 1,
  "konstató": 1,
  "pèché": 1,
  "pèchè-la": 1,
  "débouyé": 1,
  "okipé": 1,
  "lafimé": 1,
  "kanno": 1,
  "tchoulé": 1,
  "séché": 1,
  "lanmè-la-é": 1,
  "kay-la": 1,
  "nòs": 1,
  "tabak": 1,
  "plisimyé": 1,
  "milèt": 1,
  "vlopé": 1,
  "jolivans": 1,
  "koumandé": 1,
  "nègrès-la": 1,
  "plézi": 1,
  "lèt": 1,
  "nwè-la": 1,
  "graj": 1,
  "bardé": 1,
  "poumyé": 1,
  "goud": 1,
  "sourian": 1,
  "suivié": 1,
  "fós": 1,
  "kafé": 1,
  "epi": 1,
  "poté": 1,
  "madras": 1,
  "krakan": 1,
  "lenn": 1,
  "rensé": 1,
  "kuvèt": 1,
  "basinn": 1,
  "mach-la": 1,
  "flan": 1,
  "chouval-la": 1,
  "fyèv-la": 1,
  "mètri": 1,
  "méyé": 1,
  "henni": 1,
  "boutan": 1,
  "lalé": 1,
  "bèngné": 1,
  "luil": 1,
  "asisté": 1,
  "chat-la": 1,
  "koto-koto": 1,
  "makak-la": 1,
  "jalou": 1,
  "vwèl": 1,
  "vwalyé-la": 1,
  "hotè": 1,
  "twati": 1,
  "tò-lá": 1,
  "môso": 1,
  "uit": 1,
  "rakontaj": 1,
  "vandè-la": 1,
  "gout": 1,
  "réparé": 1,
  "alédouvan": 1,
  "apyé": 1,
  "fontenn": 1,
  "anko": 1,
  "poukibiten": 1,
  "hoté": 1,
  "danjé-la": 1,
  "konprinnèt": 1,
  "jèsté": 1,
  "kouyon": 1,
  "pi-a-dlo": 1,
  "granbidim": 1,
  "kanmenmsa": 1,
  "lèwwvè": 1,
  "zétwal": 1,
  "apési": 1,
  "lafyèv": 1,
  "mémwwa": 1,
  "migannaj": 1,
  "langannaj": 1,
  "chiraj": 1,
  "katèl": 1,
  "éklò": 1,
  "domino": 1,
  "balans": 1,
  "kontwa": 1,
  "pratik": 1,
  "kamo": 1,
  "pawolik": 1,
  "koudlang": 1,
  "tafyaté": 1,
  "ansiskatdé": 1,
  "jaktans": 1,
  "machann": 1,
  "kankan": 1,
  "fant": 1,
  "finèt": 1,
  "zagalas": 1,
  "voplé": 1,
  "fouben": 1,
  "filtré": 1,
  "pèsyènnri": 1,
  "jalouzi": 1,
  "magoté": 1,
  "gajé": 1,
  "tiwèt": 1,
  "konbòch": 1,
  "antrèt": 1,
  "vlen": 1,
  "vwazen": 1,
  "opéyi": 1,
  "lakouyonnri": 1,
  "asdribal": 1,
  "koutpyé": 1,
  "toudous": 1,
  "tèwbolizé": 1,
  "bazil": 1,
  "tranché": 1,
  "lagè": 1,
  "twoub": 1,
  "san-manman": 1,
  "koupmandvant": 1,
  "ponnyé-nou": 1,
  "souvènans": 1,
  "drivayé": 1,
  "agou": 1,
  "kòkma": 1,
  "tranndouz": 1,
  "lakòz": 1,
  "wouvwè": 1,
  "èksétéra": 1,
  "jalou-y": 1,
  "pipirit-chantan": 1,
  "démon": 1,
  "marinad": 1,
  "mangnétizè": 1,
  "lapérézité": 1,
  "léta": 1,
  "lisifè": 1,
  "paspété": 1,
  "tadé": 1,
  "kòltaré": 1,
  "kriyan-min": 1,
  "èspès-kalité": 1,
  "déplwayé": 1,
  "mirak": 1,
  "annawjan": 1,
  "kotéla": 1,
  "gayé": 1,
  "anho": 1,
  "montangn": 1,
  "lavandé": 1,
  "zozyo": 1,
  "épisa": 1,
  "jiké": 1,
  "jistikont": 1,
  "montré-nou": 1,
  "toutolwen": 1,
  "plibyen": 1,
  "ployé": 1,
  "vòlkan": 1,
  "fimé": 1,
  "kwè-y": 1,
  "atoultan": 1,
  "ladoutans": 1,
  "kwayans": 1,
  "fonnkè": 1,
  "mézanmi": 1,
  "pou-w": 1,
  "rémon": 1,
  "asistan": 1,
  "lorèy": 1,
  "banjo": 1,
  "moniman": 1,
  "virjilan": 1,
  "kou-la": 1,
  "chasè": 1,
  "anmwé-soukou": 1,
  "sové-mwen": 1,
  "bòt-la": 1,
  "afè": 1,
  "téléfòn": 1,
  "lanbilans": 1,
  "jandab-sentàn": 1,
  "polis-gozyé": 1,
  "lari-la": 1,
  "anmwé-anmwé": 1,
  "osoukou": 1,
  "kondoléyans": 1,
  "moun-moro": 1,
  "toutmoun-bouliki": 1,
  "kouwi": 1,
  "moun-granfon": 1,
  "désédé": 1,
  "lévakans": 1,
  "vyann-la": 1,
  "ba-li": 1,
  "òktòb": 1,
  "véyé-mwen": 1,
  "kyouyé-mwen": 1,
  "woy-yoyoy": 1,
  "kriminèl": 1,
  "mizérab": 1,
  "pè-dè-bòn-famiy": 1,
  "a-vou": 1,
  "préché-y": 1,
  "édikasyon": 1,
  "dimanch-maten": 1,
  "détwi": 1,
  "péran": 1,
  "sentann": 1,
  "fwansantiy": 1,
  "kyòkanblòk": 1,
  "chomaj": 1,
  "bontibwen": 1,
  "poch": 1,
  "paket": 1,
  "vèglaj": 1,
  "dousi": 1,
  "kyolòlò": 1,
  "zong": 1,
  "eksétéra": 1,
  "zorey": 1,
  "kankangnan": 1,
  "akitan": 1,
  "makayé": 1,
  "migan-lasa": 1,
  "konvwa-la": 1,
  "wop": 1,
  "hop": 1,
  "kòk-genm": 1,
  "henkenchyen": 1,
  "léhou": 1,
  "zépon": 1,
  "twazé": 1,
  "zéklè": 1,
  "inosan": 1,
  "sòlèy-la": 1,
  "chadwon": 1,
  "pikan": 1,
  "lakat": 1,
  "lévwa": 1,
  "anonsé": 1,
  "lézanmi": 1,
  "adyé": 1,
  "bougrès": 1,
  "gyòk": 1,
  "maladi": 1,
  "dévenn": 1,
  "soulajman": 1,
  "lanbéli": 1,
  "movétan": 1,
  "vyékò": 1,
  "mèt-a-mangnòk": 1,
  "dépalé": 1,
  "lopilans": 1,
  "makak": 1,
  "moun-dèwò": 1,
  "foutépamal": 1,
  "filé": 1,
  "lapèldéchanpyon": 1,
  "konba": 1,
  "vyéfò": 1,
  "marigalant": 1,
  "dézirad": 1,
  "wouparèt": 1,
  "andimilfason": 1,
  "kasoulé": 1,
  "konsèv": 1,
  "yon": 1,
  "nèg-a-krab": 1,
  "kabriyèlè": 1,
  "mòwnalo": 1,
  "toulézanmi": 1,
  "oho": 1,
  "wouso": 1,
  "déjiné": 1,
  "diné": 1,
  "kannari": 1,
  "rann-vou": 1,
  "malpalé-nou": 1,
  "méprizé-nou": 1,
  "kritiké-nou": 1,
  "danlérè": 1,
  "krab-la": 1,
  "pla": 1,
  "gastwonomi": 1,
  "wooo": 1,
  "wééé": 1
}